{
  "head": "head",
  "portraitScale": 0.3,
  "portraitTranslation": [ -0.5, 4.5, 0 ],
  "profileScale": 0.09,
  "profileTranslation": [ 0, 1.625, 0 ],
  "faint": "bedrock(ult_guzzlord, faint)",
  "poses": {
    "standing": {
      "poseName": "standing",
      "transformTicks": 10,
      "poseTypes": [
        "STAND",
        "NONE",
        "PORTRAIT",
        "PROFILE"
      ],
      "animations": [
        "look",
        "bedrock(ult_guzzlord, ground_idle)"
      ]
    },
    "walking": {
      "poseName": "walking",
      "transformTicks": 10,
      "poseTypes": [ "WALK" ],
      "animations": [ "bedrock(ult_guzzlord, ground_walk)" ]
    }
  }
}